routeros/__init__.py
routeros/api.py
routeros/exc.py
routeros/utils.py
routeros-0.1.0.dist-info/LICENSE
routeros-0.1.0.dist-info/WHEEL
routeros-0.1.0.dist-info/METADATA
routeros-0.1.0.dist-info/RECORD
