Metadata-Version: 2.1
Name: routeros
Version: 0.1.0
Summary: Implementation of Mikrotik API
Home-page: https://github.com/rtician/routeros
License: MIT
Author: Ramiro Tician
Author-email: ramirotician@gmail.com
Requires-Python: >=2.7
Classifier: Development Status :: 5 - Production/Stable
Classifier: Intended Audience :: Developers
Classifier: License :: OSI Approved :: MIT License
Classifier: Operating System :: OS Independent
Classifier: Programming Language :: Python :: 2
Classifier: Programming Language :: Python :: 2.7
Classifier: Programming Language :: Python :: 3
Classifier: Programming Language :: Python :: 3.4
Classifier: Programming Language :: Python :: 3.5
Classifier: Programming Language :: Python :: 3.6
Classifier: Programming Language :: Python :: 3.7
Classifier: Programming Language :: Python :: 3.8
Classifier: Topic :: Software Development :: Libraries
Project-URL: Repository, https://github.com/rtician/routeros
